{"children":[{"name":"Building, Construction & Heating","class":"Category","children":[{"name":"Reduce energy consumption from building heating","class":"Actions","children":[{"name":"Renewable heat Bio","class":"savings","size":0.4,"color":"Building, Construction & Heating","label":["Renewable heat Bio"]},{"name":"Renewable heat Solar","class":"savings","size":0.2,"color":"Building, Construction & Heating","label":["Renewable heat Solar"]}]},{"name":"Reduce embodied emissions from buildings","class":"Actions","children":[{"name":"New buildings","class":"savings","size":0.5,"color":"Building, Construction & Heating","label":["New buildings"]}]}]},{"name":"Energy & Fuels","class":"Category","children":[{"name":"Scale low-emission power generation","class":"Actions","children":[{"name":"Solar energy","class":"savings","size":3,"color":"Energy & Fuels","label":["Solar energy"]},{"name":"Wind energy","class":"savings","size":2.6,"color":"Energy & Fuels","label":["Wind energy"]},{"name":"Hydropower","class":"savings","size":1.9,"color":"Energy & Fuels","label":["Hydropower"]},{"name":"Nuclear","class":"savings","size":0.9,"color":"Energy & Fuels","label":["Nuclear"]},{"name":"Bio Energy ","class":"savings","size":0.9,"color":"Energy & Fuels","label":["Bio Energy "]},{"name":"Geothermal","class":"savings","size":0.7,"color":"Energy & Fuels","label":["Geothermal"]}]},{"name":"Increase energy efficiency","class":"Actions","children":[{"name":"Appliances","class":"savings","size":3.3,"color":"Energy & Fuels","label":["Appliances"]},{"name":"Lighting","class":"savings","size":0.7,"color":"Energy & Fuels","label":["Lighting"]},{"name":"Existing Buildings","class":"savings","size":0.7,"color":"Energy & Fuels","label":["Existing Buildings"]}]},{"name":"Eliminate methane emissions","class":"Actions","children":[{"name":"Methane from Coal","class":"savings","size":1.8,"color":"Energy & Fuels","label":["Methane from Coal"]},{"name":"Methane from Oil & Gas","class":"savings","size":0.4,"color":"Energy & Fuels","label":["Methane from Oil & Gas"]}]}]},{"name":"Industry","class":"Category","children":[{"name":"Reduce energy consumption","class":"Actions","children":[{"name":"Direct Energy efficiency","class":"savings","size":2.2,"color":"Industry","label":["Direct Energy efficiency"]},{"name":"Indirect Energy efficiency","class":"savings","size":1.9,"color":"Industry","label":["Indirect Energy efficiency"]}]},{"name":"Increase sustainable material use and efficiency","class":"Actions","children":[{"name":"Renewable Hear","class":"savings","size":0.5,"color":"Industry","label":["Renewable Hear"]}]},{"name":"Scale low-carbon heating processes","class":"Actions","children":[{"name":"Scale low-carbon heating processes","class":"savings","size":1,"color":"Industry","label":["Scale low-carbon heating processes"]}]}]},{"name":"Land use","class":"Category","children":[{"name":"Reduce land degradation","class":"Actions","children":[{"name":"Reduce deforestation","class":"savings","size":3,"color":"Land use","label":["Reduce deforestation"]}]},{"name":"Reduce cropland/forest burning","class":"Actions","children":[{"name":"Cropland management","class":"savings","size":0.7,"color":"Land use","label":["Cropland management"]},{"name":"Peatland degradation and fires","class":"savings","size":0.5,"color":"Land use","label":["Peatland degradation and fires"]}]},{"name":"Scale sustainable food production","class":"Actions","children":[{"name":"Shifting dietary patterns","class":"savings","size":0.4,"color":"Land use","label":["Shifting dietary patterns"]},{"name":"Rice management","class":"savings","size":0.2,"color":"Land use","label":["Rice management"]},{"name":"Livestock management","class":"savings","size":0.2,"color":"Land use","label":["Livestock management"]}]},{"name":"Increase net-zero waste mgt. practices","class":"Actions","children":[{"name":"Food loss and waste","class":"savings","size":1,"color":"Land use","label":["Food loss and waste"]},{"name":"Landfill gas recovery","class":"savings","size":0.4,"color":"Land use","label":["Landfill gas recovery"]}]}]},{"name":"Negative Emissions Solution","class":"Category","children":[{"name":"Accelerate afforestation and reforestation","class":"Actions","children":[{"name":"Forest","class":"savings","size":1.6,"color":"Negative Emissions Solution","label":["Forest"]},{"name":"Agricultrual land","class":"savings","size":0.8,"color":"Negative Emissions Solution","label":["Agricultrual land"]}]},{"name":"Scale ocean and soil carbon sequestration solutions","class":"Actions","children":[{"name":"CCS from industry","class":"savings","size":1.2,"color":"Negative Emissions Solution","label":["CCS from industry"]},{"name":"CCS from energy","class":"savings","size":0.5,"color":"Negative Emissions Solution","label":["CCS from energy"]},{"name":"Bioenergy with CCS","class":"savings","size":0.3,"color":"Negative Emissions Solution","label":["Bioenergy with CCS"]}]},{"name":"Integrate CCU/S technologies","class":"Actions","children":[{"name":"Enhanced weathing measures","class":"savings","size":0.7,"color":"Negative Emissions Solution","label":["Enhanced weathing measures"]},{"name":"Biochar","class":"savings","size":0.2,"color":"Negative Emissions Solution","label":["Biochar"]}]}]},{"name":"Transportation","class":"Category","children":[{"name":"Reduce heavy-duty transport emissions","class":"Actions","children":[{"name":"EVs and fuel efficiency","class":"savings","size":2.5,"color":"Transportation","label":["EVs and fuel efficiency"]}]},{"name":"Reduce light-duty transport emissions","class":"Actions","size":2,"color":"Transportation","label":[""]}]}]}